LICENSE
MANIFEST.in
README.md
setup.py
unit_parser/__init__.py
unit_parser/convert.py
unit_parser/test_units.py
unit_parser/units.py
unit_parser.egg-info/PKG-INFO
unit_parser.egg-info/SOURCES.txt
unit_parser.egg-info/dependency_links.txt
unit_parser.egg-info/entry_points.txt
unit_parser.egg-info/not-zip-safe
unit_parser.egg-info/top_level.txt
unit_parser/units/units.txt