Metadata-Version: 1.0
Name: unit-parser
Version: 0.1
Summary: Unit Parser and Conversions
Home-page: https://github.com/rwilson4/unit_parser
Author: Bob Wilson
Author-email: bob@causalityinc.com
License: Apache 2.0
Keywords: unit,conversion,parsing,physics,engineering
Platform: UNKNOWN
